cropmerge/__init__.py
cropmerge/crop.py
cropmerge/merge.py
cropmerge-0.1.0.dist-info/METADATA
cropmerge-0.1.0.dist-info/WHEEL
cropmerge-0.1.0.dist-info/licenses/COPYING
cropmerge-0.1.0.dist-info/RECORD
